jaxmarl/__init__.py
jaxmarl/registration.py
jaxmarl/environments/__init__.py
jaxmarl/environments/multi_agent_env.py
jaxmarl/environments/spaces.py
jaxmarl/environments/coin_game/__init__.py
jaxmarl/environments/coin_game/coin_game.py
jaxmarl/environments/hanabi/__init__.py
jaxmarl/environments/hanabi/hanabi.py
jaxmarl/environments/hanabi/hanabi_game.py
jaxmarl/environments/hanabi/manual_game.py
jaxmarl/environments/hanabi/manual_game_human_agents.py
jaxmarl/environments/hanabi/pretrained/__init__.py
jaxmarl/environments/hanabi/pretrained/obl_r2d2_agent.py
jaxmarl/environments/hanabi/pretrained/obl_r2d2_agent_test.py
jaxmarl/environments/jaxnav/__init__.py
jaxmarl/environments/jaxnav/jaxnav_env.py
jaxmarl/environments/jaxnav/jaxnav_graph_utils.py
jaxmarl/environments/jaxnav/jaxnav_singletons.py
jaxmarl/environments/jaxnav/jaxnav_ued_utils.py
jaxmarl/environments/jaxnav/jaxnav_utils.py
jaxmarl/environments/jaxnav/jaxnav_viz.py
jaxmarl/environments/jaxnav/maps/__init__.py
jaxmarl/environments/jaxnav/maps/grid_map.py
jaxmarl/environments/jaxnav/maps/map.py
jaxmarl/environments/jaxnav/maps/map_registration.py
jaxmarl/environments/jaxnav/maps/polygon_map.py
jaxmarl/environments/mabrax/__init__.py
jaxmarl/environments/mabrax/mabrax_env.py
jaxmarl/environments/mabrax/mappings.py
jaxmarl/environments/mpe/__init__.py
jaxmarl/environments/mpe/default_params.py
jaxmarl/environments/mpe/mpe_visualizer.py
jaxmarl/environments/mpe/simple.py
jaxmarl/environments/mpe/simple_adversary.py
jaxmarl/environments/mpe/simple_crypto.py
jaxmarl/environments/mpe/simple_facmac.py
jaxmarl/environments/mpe/simple_push.py
jaxmarl/environments/mpe/simple_reference.py
jaxmarl/environments/mpe/simple_speaker_listener.py
jaxmarl/environments/mpe/simple_spread.py
jaxmarl/environments/mpe/simple_tag.py
jaxmarl/environments/mpe/simple_world_comm.py
jaxmarl/environments/overcooked/__init__.py
jaxmarl/environments/overcooked/common.py
jaxmarl/environments/overcooked/interactive.py
jaxmarl-0.1.0.dist-info/licenses/LICENSE
jaxmarl-0.1.0.dist-info/METADATA
jaxmarl-0.1.0.dist-info/WHEEL
jaxmarl-0.1.0.dist-info/top_level.txt
jaxmarl-0.1.0.dist-info/RECORD
