Metadata-Version: 2.4
Name: jaxmarl
Version: 0.1.0
Summary: Multi-Agent Reinforcement Learning with JAX
Author-email: Foerster Lab for AI Research <arutherford@robots.ox.ac.uk>
License: Apache License
Project-URL: Homepage, https://github.com/FLAIROx/JaxMARL
Project-URL: Bug Tracker, https://github.com/FLAIROx/JaxMARL/issues
Classifier: Programming Language :: Python
Classifier: Programming Language :: Python :: 3
Classifier: Programming Language :: Python :: 3.10
Classifier: Intended Audience :: Developers
Classifier: Intended Audience :: Science/Research
Classifier: Operating System :: OS Independent
Classifier: Topic :: Scientific/Engineering :: Artificial Intelligence
Classifier: Topic :: Software Development :: Libraries :: Python Modules
Classifier: License :: OSI Approved :: Apache Software License
Requires-Python: >=3.10
License-File: LICENSE
Requires-Dist: jax<=0.4.38
Requires-Dist: jaxlib
Requires-Dist: flax
Requires-Dist: safetensors
Requires-Dist: chex
Requires-Dist: brax==0.10.3
Requires-Dist: mujoco==3.1.3
Requires-Dist: matplotlib
Requires-Dist: pillow
Requires-Dist: scipy<=1.12
Requires-Dist: gymnax
Provides-Extra: algs
Requires-Dist: optax; extra == "algs"
Requires-Dist: distrax; extra == "algs"
Requires-Dist: flashbax==0.1.0; extra == "algs"
Requires-Dist: wandb; extra == "algs"
Requires-Dist: hydra-core>=1.3.2; extra == "algs"
Requires-Dist: omegaconf>=2.3.0; extra == "algs"
Requires-Dist: pettingzoo>=1.24.3; extra == "algs"
Requires-Dist: tqdm>=4.66.0; extra == "algs"
Provides-Extra: dev
Requires-Dist: pytest; extra == "dev"
Requires-Dist: pygame; extra == "dev"
Dynamic: license-file
